.gitignore
CHANGES.txt
LICENSE.txt
MANIFEST.in
README.txt
TODO.txt
setup.cfg
setup.py
Akhet.egg-info/PKG-INFO
Akhet.egg-info/SOURCES.txt
Akhet.egg-info/dependency_links.txt
Akhet.egg-info/entry_points.txt
Akhet.egg-info/not-zip-safe
Akhet.egg-info/requires.txt
Akhet.egg-info/top_level.txt
akhet/__init__.py
akhet/pony.py
akhet/static.py
akhet/urlgenerator.py
akhet/demo/TECH.txt
akhet/demo/__init__.py
akhet/demo/__main__.py
akhet/demo/requirements.txt
akhet/demo/subscribers.py
akhet/demo/tests.py
akhet/demo/views.py
akhet/demo/lib/__init__.py
akhet/demo/lib/helpers.py
akhet/demo/static/favicon.ico
akhet/demo/static/images/pyramid-negative.png
akhet/demo/static/stylesheets/default.css
akhet/demo/static/stylesheets/reset.css
akhet/demo/templates/index.html
akhet/demo/templates/site.html
akhet/tests/__init__.py
akhet/tests/make_test_app.sh
akhet/tests/test_init.py
akhet/tests/test_static.py
akhet/tests/test_urlgenerator.py
docs/Makefile
docs/changes.rst
docs/conf.py
docs/index.rst
docs/links.rst
docs/rant_scaffold.rst
docs/demo/content.rst
docs/demo/details.rst
docs/demo/index.rst
docs/demo/usage.rst
docs/demo/usage.rst1
docs/library/index.rst
docs/library/pony.rst
docs/library/static.rst
docs/library/urlgenerator.rst
unfinished/breadcrumbs.rst
unfinished/my-env-filter.sh
unfinished/route_directive.py
unfinished/usage.rst