Metadata-Version: 1.0
Name: Akhet
Version: 2.0
Summary: A Pyramid library and demo app with a Pylons-inspired API.
Home-page: https://bitbucket.org/sluggo/akhet
Author: Mike Orr
Author-email: sluggoster@gmail.com
License: MIT
Keywords: web wsgi pylons pyramid
Platform: UNKNOWN
Classifier: Intended Audience :: Developers
Classifier: Framework :: Pylons
Classifier: Programming Language :: Python
Classifier: License :: OSI Approved :: MIT License
